lmdbm/__init__.py
lmdbm/lmdbm.py
lmdbm/py.typed
lmdbm_lockable-0.0.5.dist-info/METADATA
lmdbm_lockable-0.0.5.dist-info/WHEEL
lmdbm_lockable-0.0.5.dist-info/top_level.txt
lmdbm_lockable-0.0.5.dist-info/zip-safe
lmdbm_lockable-0.0.5.dist-info/RECORD
