Metadata-Version: 2.1
Name: lmdbm-lockable
Version: 0.0.5
Summary: Python DBM style wrapper around LMDB (Lightning Memory-Mapped Database)
Home-page: https://github.com/Dobatymo/lmdb-python-dbm
Author: Dobatymo
Classifier: Intended Audience :: Developers
Classifier: License :: OSI Approved :: ISC License (ISCL)
Classifier: Operating System :: OS Independent
Classifier: Programming Language :: Python :: 3
Classifier: Topic :: Database
Requires-Python: >=3.6
Requires-Dist: lmdb
Provides-Extra: dev
Requires-Dist: isort ; extra == 'dev'
Requires-Dist: genutility ; extra == 'dev'
